LICENSE
MANIFEST.in
Makefile
README.rst
requirements.txt
setup.cfg
setup.py
enlightns_cli.egg-info/PKG-INFO
enlightns_cli.egg-info/SOURCES.txt
enlightns_cli.egg-info/dependency_links.txt
enlightns_cli.egg-info/entry_points.txt
enlightns_cli.egg-info/not-zip-safe
enlightns_cli.egg-info/requires.txt
enlightns_cli.egg-info/top_level.txt
enscli/__init__.py
enscli/settings.py
enscli/rest/__init__.py
enscli/rest/services.py
enscli/scripts/__init__.py
enscli/scripts/bash_complete.sh
enscli/scripts/cli.py
enscli/tests/__init__.py
enscli/tests/conftest.py
enscli/tests/test_helloworld.py
enscli/tools/__init__.py
enscli/tools/configurations.py
enscli/tools/cron.py
enscli/tools/exceptions.py
enscli/tools/interfaces.py
enscli/tools/messages.py
enscli/tools/resolver.py