Metadata-Version: 1.1
Name: enlightns-cli
Version: 0.0.21
Summary: EnlightNS.com Command Line Interface.
Home-page: http://enlightns.com/
Author: Dominick Rivard
Author-email: support@enlightns.com
License: GPLv3
Platform: UNKNOWN
Classifier: Development Status :: 4 - Beta
Classifier: Intended Audience :: End Users/Desktop
Classifier: Intended Audience :: Developers
Classifier: Intended Audience :: System Administrators
Classifier: Natural Language :: English
Classifier: License :: OSI Approved :: GNU General Public License v3 or later (GPLv3+)
Classifier: Programming Language :: Python
Classifier: Programming Language :: Python :: 2.7
